{
  "$schema": "https://json-structure.org/meta/core/v0/#",
  "$id": "https://raw.githubusercontent.com/api-evangelist/dynatrace/refs/heads/main/json-structure/log-monitoring-api-v2-log-aggregate-group-structure.json",
  "description": "A single aggregation group result.",
  "type": "object",
  "properties": {
    "groupByFields": {
      "type": "object",
      "description": "The field values that define this aggregation group. Keys are the groupBy field names, values are the field values for this group.",
      "additionalProperties": {
        "type": "string"
      },
      "example": {}
    },
    "count": {
      "type": "int64",
      "description": "The number of log records in this aggregation group.",
      "example": 500
    }
  },
  "name": "LogAggregateGroup"
}